Orange3_Associate-1.4.0-py3.13-nspkg.pth
orangecontrib/associate/__init__.py
orangecontrib/associate/_fpgrowth.cpp
orangecontrib/associate/_fpgrowth.cpython-313-x86_64-linux-gnu.so
orangecontrib/associate/_fpgrowth.pyx
orangecontrib/associate/fpgrowth.py
orangecontrib/associate/widgets/__init__.py
orangecontrib/associate/widgets/owassociate.py
orangecontrib/associate/widgets/owitemsets.py
orangecontrib/associate/widgets/icons/AssociationRules.svg
orangecontrib/associate/widgets/icons/FrequentItemsets.svg
orangecontrib/associate/widgets/tests/__init__.py
orangecontrib/associate/widgets/tests/test_owassociate.py
orangecontrib/associate/widgets/tests/data/market-basket.tab
orange3_associate-1.4.0.dist-info/METADATA
orange3_associate-1.4.0.dist-info/WHEEL
orange3_associate-1.4.0.dist-info/entry_points.txt
orange3_associate-1.4.0.dist-info/namespace_packages.txt
orange3_associate-1.4.0.dist-info/top_level.txt
orange3_associate-1.4.0.dist-info/RECORD
orange3_associate-1.4.0.dist-info/licenses/LICENSE
